ggtranslate
