Metadata-Version: 2.1
Name: ggtranslate
Version: 1.0.4
Summary: translate anything use google api
Home-page: http://www.super1207.top
Author: super1207
Author-email: pengyao1210@gmail.com
License: MIT Licence
Keywords: pip,ggtranslate,google,translate
Platform: any
